CHANGES.txt
COPYING
INSTALL.txt
MANIFEST.in
README.txt
setup.py
hwit/__init__.py
hwit/checks/__init__.py
hwit/checks/common.py
hwit/checks/test/__init__.py
hwit/checks/test/test_typertest.py
hwit/core/__init__.py
hwit/core/about.py
hwit/core/console.py
hwit/core/context.py
hwit/core/generator.py
hwit/core/model.py
hwit/core/parser.py
hwit/core/settings.py
hwit/core/doc/Makefile
hwit/core/doc/__init__.py
hwit/core/doc/conf.py
hwit/core/doc/hwit-dev.rst
hwit/core/doc/hwit-spec.rst
hwit/core/doc/index.rst
hwit/core/doc/make.bat
hwit/core/doc/_static/hwit_icon-96x96.png
hwit/core/graphics/hwit_icon-192x192.svg
hwit/core/test/__init__.py
hwit/core/test/test_console.py
hwit/core/test/test_container.py
hwit/core/test/test_context.py
hwit/core/test/test_generator.py
hwit/core/test/ref/basic.hwit
hwit/core/test/ref/blank.hwit
hwit/core/test/ref/corrugation-3003.hwit
hwit/core/test/ref/empty.hwit
hwit/core/test/ref/hwit-partial.hwit
hwit/core/test/ref/osvaldo-3915.hwit
hwit/core/test/ref/risky.hwit
hwit/core/test/ref/scout_camp.tsv
hwit/core/test/ref/small.hwit
hwit/core/test/ref/underskirts-3915.hwit
hwit/core/utils/__init__.py
hwit/core/utils/cluster.py
hwit/core/utils/happenstance.py
hwit/core/utils/hwit_console.py
hwit/core/utils/ingest.py
hwit/core/utils/triage.py
hwit_core.egg-info/PKG-INFO
hwit_core.egg-info/SOURCES.txt
hwit_core.egg-info/dependency_links.txt
hwit_core.egg-info/entry_points.txt
hwit_core.egg-info/namespace_packages.txt
hwit_core.egg-info/top_level.txt