Metadata-Version: 1.1
Name: hwit-core
Version: 0.02-r00672
Summary: Here's What I Think; core library
Home-page: http://hwit.org
Author: D Haynes
Author-email: tundish@thuswise.org
License: COPYING
Platform: UNKNOWN
Classifier: Operating System :: OS Independent
Classifier: Programming Language :: Python :: 2.5
Classifier: Programming Language :: Python :: 2.6
Classifier: Programming Language :: Python :: 2.7
Classifier: License :: OSI Approved :: GNU General Public License v3 or later (GPLv3+)
